mistinguette/__init__.py
mistinguette/_modidx.py
mistinguette/core.py
mistinguette/toolloop.py
mistinguette-0.0.2.dist-info/licenses/LICENSE
mistinguette-0.0.2.dist-info/METADATA
mistinguette-0.0.2.dist-info/WHEEL
mistinguette-0.0.2.dist-info/entry_points.txt
mistinguette-0.0.2.dist-info/top_level.txt
mistinguette-0.0.2.dist-info/RECORD
